xata/__init__.py
xata/api/__init__.py
xata/api/authentication.py
xata/api/branch.py
xata/api/databases.py
xata/api/files.py
xata/api/invites.py
xata/api/migrations.py
xata/api/oauth.py
xata/api/records.py
xata/api/search_and_filter.py
xata/api/sql.py
xata/api/table.py
xata/api/users.py
xata/api/workspaces.py
xata/api_request.py
xata/api_response.py
xata/client.py
xata/errors.py
xata/helpers.py
xata-1.3.4.dist-info/LICENSE
xata-1.3.4.dist-info/METADATA
xata-1.3.4.dist-info/NOTICE
xata-1.3.4.dist-info/WHEEL
xata-1.3.4.dist-info/RECORD
