Metadata-Version: 2.1
Name: xata
Version: 1.3.4
Summary: Python SDK for Xata.io
License: Apache-2.0
Author: Xata
Author-email: support@xata.io
Requires-Python: >=3.8,<4.0
Classifier: License :: OSI Approved :: Apache Software License
Classifier: Programming Language :: Python :: 3
Classifier: Programming Language :: Python :: 3.8
Classifier: Programming Language :: Python :: 3.9
Classifier: Programming Language :: Python :: 3.10
Classifier: Programming Language :: Python :: 3.11
Classifier: Programming Language :: Python :: 3.12
Requires-Dist: deprecation (>=2.1.0,<3.0.0)
Requires-Dist: orjson (>=3.8.1,<4.0.0)
Requires-Dist: python-dotenv (>=0.21,<2.0)
Requires-Dist: requests (>=2.28.1,<3.0.0)
Project-URL: Documentation, https://xata-py.readthedocs.io
